[
  {
    "Cidade": "Jaguarão do Sul",
    "Estado": "Rio Grande do Sul",
    "Abreviatura da Instituição": "IFSul",
    "Nome da Instituição/Tipo": "Instituto Federal De Educação. Ciência E Tecnologia Sul-Rio-Grandense - Campus Jaguarão",
    "Setor": "Outros",
    "Contato": "",
    "Site": "https://www.jaguarao.ifsul.edu.br/",
    "E-mail de contato": "gabinete.reitoria@ifsul.edu.br",
    "latitude": null,
    "longitude": null,
    "coordenadas_status": "fora_rs"
  },
  {
    "Cidade": "Camaquã",
    "Estado": "Rio Grande do Sul",
    "Abreviatura da Instituição": "IFSul",
    "Nome da Instituição/Tipo": "Instituto Federal De Educação. Ciência E Tecnologia Sul-Rio-Grandense - Campus Camaqua",
    "Setor": "Outros",
    "Contato": "",
    "Site": "https://intranet.ifsul.edu.br/catalogo/campus/3",
    "E-mail de contato": "gabinete.reitoria@ifsul.edu.br",
    "latitude": null,
    "longitude": null,
    "coordenadas_status": "fora_rs"
  },
  {
    "Cidade": "Viamão",
    "Estado": "Rio Grande do Sul",
    "Abreviatura da Instituição": "IFRS",
    "Nome da Instituição/Tipo": "Instituto Federal De Educação. Ciência E Tecnologia Do Rio Grande Do Sul - Campus Viamão",
    "Setor": "Outros",
    "Contato": "",
    "Site": "https://ifrs.edu.br/viamao/",
    "E-mail de contato": "gabinete@ifrs.edu.br",
    "latitude": null,
    "longitude": null,
    "coordenadas_status": "fora_rs"
  },
  {
    "Cidade": "São Borja",
    "Estado": "Rio Grande do Sul",
    "Abreviatura da Instituição": "UNIPAMPA",
    "Nome da Instituição/Tipo": "Fundação Universidade Federal Do Pampa Unipampa - Campus São Borja",
    "Setor": "Outros",
    "Contato": "",
    "Site": "https://unipampa.edu.br/portal/",
    "E-mail de contato": "gabinete.reitoria@unipampa.edu.br",
    "latitude": null,